KratosMultiphysics/StatisticsApplication/__init__.py
KratosMultiphysics/StatisticsApplication/method_utilities.py
KratosMultiphysics/StatisticsApplication/spatial_statistics_process.py
KratosMultiphysics/StatisticsApplication/spatial_utilities.py
KratosMultiphysics/StatisticsApplication/temporal_statistics_process.py
KratosMultiphysics/StatisticsApplication/temporal_utilities.py
KratosMultiphysics/StatisticsApplication/test_utilities.py
KratosMultiphysics/.libs/KratosStatisticsApplication.pyd
KratosMultiphysics/.libs/KratosStatisticsCore.dll
KratosMultiphysics/.libs/KratosStatisticsCore.lib
kratosstatisticsapplication-10.4.0.dist-info/METADATA
kratosstatisticsapplication-10.4.0.dist-info/WHEEL
kratosstatisticsapplication-10.4.0.dist-info/RECORD
